pytaggit/__init__.py
pytaggit/taggit.py
pytaggit-1.0.0.dist-info/LICENSE
pytaggit-1.0.0.dist-info/WHEEL
pytaggit-1.0.0.dist-info/METADATA
pytaggit-1.0.0.dist-info/RECORD
