Metadata-Version: 2.1
Name: pytaggit
Version: 1.0.0
Summary: Applies tagging to organize files.
Home-page: https://github.com/savageGrant/taggit
License: MIT
Keywords: tagging,tags,tag
Author: Grant Savage
Requires-Python: >=3.7,<4.0
Classifier: License :: OSI Approved :: MIT License
Classifier: Programming Language :: Python :: 3
Classifier: Programming Language :: Python :: 3 :: Only
Classifier: Programming Language :: Python :: 3.10
Classifier: Programming Language :: Python :: 3.7
Classifier: Programming Language :: Python :: 3.8
Classifier: Programming Language :: Python :: 3.9
Classifier: Topic :: Software Development :: Libraries :: Python Modules
Requires-Dist: biplist (>=1.0.0,<2.0.0)
Requires-Dist: flake8 (>=4.0.1,<5.0.0)
Requires-Dist: xattr (>=0.9.9,<0.10.0)
Project-URL: Repository, https://github.com/savageGrant/taggit
